aquasystems/__init__.py
aquasystems/mqtt.py
aquasystems/mqtt_test.py
aquasystems/timer.py
aquasystems_driver-0.0.3.dist-info/DESCRIPTION.rst
aquasystems_driver-0.0.3.dist-info/METADATA
aquasystems_driver-0.0.3.dist-info/RECORD
aquasystems_driver-0.0.3.dist-info/WHEEL
aquasystems_driver-0.0.3.dist-info/metadata.json
aquasystems_driver-0.0.3.dist-info/top_level.txt
