Metadata-Version: 2.0
Name: aquasystems-driver
Version: 0.0.3
Summary: MQTT Bluetooth Service for Aqua Systems Tap Timer
Home-page: https://github.com/sammchardy/aquasystems-driver
Author: Sam McHardy
Author-email: UNKNOWN
License: MIT
Keywords: "aqua systems" yardeen bluetooth "home assistant" "tap timer"
Platform: UNKNOWN
Classifier: Intended Audience :: Developers
Classifier: License :: OSI Approved :: MIT License
Classifier: Operating System :: OS Independent
Classifier: Programming Language :: Python :: 3
Classifier: Programming Language :: Python :: 3.5
Classifier: Programming Language :: Python :: 3.6
Classifier: Programming Language :: Python
Classifier: Topic :: Software Development :: Libraries :: Python Modules
Requires-Dist: Adafruit-BluefruitLE
Requires-Dist: hbmqtt
